{
    "bsc-testnet": {
        "stakingTokenAddress": "0x337610d27c682e347c9cd60bd4b3b107c9d34ddd",
        "rewardTokenAddress": "0x337610d27c682e347c9cd60bd4b3b107c9d34ddd",
        "startTime": 1634903600,
        "rewardTokenAmount": 1,
        "minTimeToStake": 1,
        "farmPeriod": 10,
        "isEarlyWithdrawAllowed": true,
        "penaltyType": 2,
        "congressAddress": "0xb79B84B38157378fdce05D41bF125942b16a8D1F",
        "stakeFeePercent": 0,
        "rewardFeePercent": 0,
        "flatFeeAmount": 0.75,
        "feeCollector": "0x85537a2c9712B0E9b2fb34C24042DD326dd469bF",
        "isFlatFeeAllowed": true
    }
}
